jsConsole/__init__.py
jsConsole/internal/__init__.py
jsConsole/internal/config.py
jsConsole/internal/exceptions.py
jsConsole/internal/browser/__init__.py
jsConsole/internal/browser/chrome_executable.py
jsConsole/internal/browser/informations.py
jsConsole/internal/browser/launch.py
jsConsole/internal/javascript/__init__.py
jsConsole/internal/javascript/classes.py
jsConsole/internal/javascript/execute_js.py
jsConsole-1.0.2.dist-info/LICENSE
jsConsole-1.0.2.dist-info/METADATA
jsConsole-1.0.2.dist-info/WHEEL
jsConsole-1.0.2.dist-info/top_level.txt
jsConsole-1.0.2.dist-info/RECORD
