Metadata-Version: 2.1
Name: jsConsole
Version: 1.0.2
Summary: A JS Console written for and in python
Home-page: https://github.com/Animenosekai/jsConsole
Author: Anime no Sekai
Author-email: niichannomail@gmail.com
License: MIT
Download-URL: https://github.com/Animenosekai/jsConsole/archive/v1.0.tar.gz
Keywords: javascript, selenium, pyppeteer, js, jsconsole, javascriptconsole, animenosekai, pythontojavascript
Platform: UNKNOWN
Classifier: Development Status :: 4 - Beta
Classifier: License :: OSI Approved :: MIT License
Classifier: Programming Language :: Python :: 3
Classifier: Programming Language :: Python :: 3.4
Classifier: Programming Language :: Python :: 3.5
Classifier: Programming Language :: Python :: 3.6
Classifier: Programming Language :: Python :: 3.7
Classifier: Programming Language :: Python :: 3.8
Requires-Dist: psutil
